nishant_outlier_76.py
nishant_outlier_76-1.0.2.data/scripts/outliers_cli
nishant_outlier_76-1.0.2.dist-info/LICENSE
nishant_outlier_76-1.0.2.dist-info/METADATA
nishant_outlier_76-1.0.2.dist-info/WHEEL
nishant_outlier_76-1.0.2.dist-info/top_level.txt
nishant_outlier_76-1.0.2.dist-info/RECORD
