Metadata-Version: 2.1
Name: nishant-outlier-76
Version: 1.0.2
Summary: Outlier Removal Using Z-score or IQR
Home-page: https://github.com/nishu195/nishant_outlier_76
Author: Nishant Goel
Author-email: ngoel_be17@thapar.edu
License: UNKNOWN
Keywords: command-line,Outliers,outlier-removal,row-removal
Platform: UNKNOWN
Classifier: Programming Language :: Python :: 3
Classifier: License :: OSI Approved :: MIT License
Classifier: Operating System :: OS Independent
Requires-Python: >=3.6
Requires-Dist: numpy
Requires-Dist: pandas
